COCOpy/__init__.py
COCOpy_1_pietrow-0.0.1.dist-info/METADATA
COCOpy_1_pietrow-0.0.1.dist-info/WHEEL
COCOpy_1_pietrow-0.0.1.dist-info/top_level.txt
COCOpy_1_pietrow-0.0.1.dist-info/RECORD
