Metadata-Version: 2.1
Name: COCOpy-1-pietrow
Version: 0.0.1
Summary: COlor COllapsed Plotting software
Home-page: https://github.com/AlexPietrow/COCO/tree/master/Python
Author: A.G.M. Pietrow
Author-email: Alex.pietrow@astro.su.se
License: UNKNOWN
Platform: UNKNOWN
Classifier: Programming Language :: Python :: 2.7
Classifier: License :: OSI Approved :: MIT License
Classifier: Operating System :: OS Independent
